byted_torch_monitor-0.2.dist-info/licenses/LICENSE
bytedmemfd/__init__.py
byted_torch_monitor-0.2.dist-info/METADATA
byted_torch_monitor-0.2.dist-info/WHEEL
byted_torch_monitor-0.2.dist-info/top_level.txt
byted_torch_monitor-0.2.dist-info/RECORD
